AUTHORS.rst
CONTRIBUTING.rst
HISTORY.rst
LICENSE
MANIFEST.in
README.rst
setup.cfg
setup.py
profile_middleware.egg-info/PKG-INFO
profile_middleware.egg-info/SOURCES.txt
profile_middleware.egg-info/dependency_links.txt
profile_middleware.egg-info/not-zip-safe
profile_middleware.egg-info/top_level.txt
profiler/__init__.py
profiler/middleware.py
profiler/models.py
profiler/static/css/profiler.css
profiler/static/css/profiler/jquery.dataTables.css
profiler/static/img/profiler/back_disabled.png
profiler/static/img/profiler/back_enabled.png
profiler/static/img/profiler/back_enabled_hover.png
profiler/static/img/profiler/forward_disabled.png
profiler/static/img/profiler/forward_enabled.png
profiler/static/img/profiler/forward_enabled_hover.png
profiler/static/img/profiler/sort_asc.png
profiler/static/img/profiler/sort_asc_disabled.png
profiler/static/img/profiler/sort_both.png
profiler/static/img/profiler/sort_desc.png
profiler/static/img/profiler/sort_desc_disabled.png
profiler/static/js/profiler.js
profiler/static/js/profiler/jquery-1.11.0.min.js
profiler/static/js/profiler/jquery.dataTables.js
profiler/templates/profiler/base.html
profiler/templates/profiler/profiler.html