Metadata-Version: 1.1
Name: profile-middleware
Version: 0.2.6
Summary: Profiler for django views
Home-page: https://github.com/vinu76jsr/django_profiler
Author: Vaibhav Mishra
Author-email: vinu76jsr@gmail.com
License: BSD
Keywords: profiler
Platform: UNKNOWN
Classifier: Development Status :: 2 - Pre-Alpha
Classifier: Framework :: Django
Classifier: Intended Audience :: Developers
Classifier: License :: OSI Approved :: BSD License
Classifier: Natural Language :: English
Classifier: Programming Language :: Python :: 2
Classifier: Programming Language :: Python :: 2.6
Classifier: Programming Language :: Python :: 2.7
Classifier: Programming Language :: Python :: 3
Classifier: Programming Language :: Python :: 3.3
